pebbles_bot/__init__.py
pebbles_bot/pb_main.py
pebbles_bot/pb_tools.py
pebbles_bot/pebot.py
pebbles_bot-0.3.3.dist-info/LICENSE
pebbles_bot-0.3.3.dist-info/METADATA
pebbles_bot-0.3.3.dist-info/WHEEL
pebbles_bot-0.3.3.dist-info/entry_points.txt
pebbles_bot-0.3.3.dist-info/top_level.txt
pebbles_bot-0.3.3.dist-info/RECORD
