Metadata-Version: 2.1
Name: pebbles-bot
Version: 0.3.3
Summary: Telegram bot that runs Linux shell commands
Home-page: https://github.com/Lab-Brat/pyLookout
Author: Lab-Brat
Author-email: labbrat_social@pm.me
License: MIT
Classifier: License :: OSI Approved :: MIT License
Classifier: Programming Language :: Python :: 3.10
Classifier: Operating System :: POSIX :: Linux
Requires-Python: >=3.6
License-File: LICENSE
Requires-Dist: pytelegrambotapi
Requires-Dist: paramiko
Requires-Dist: pyyaml
